{"pagelen": 50, "values": [{"update": {"description": "AWS credentials and user management has been moved to an admin page", "title": "New administration page", "destination": {"commit": {"hash": "ecc7c5800779", "type": "commit", "links": {"self": {"href": "data/repositories/osrf/cloudsim-legacy/commit/ecc7c5800779.json"}, "html": {"href": "#!/osrf/cloudsim-legacy/commits/ecc7c5800779"}}}, "repository": {"links": {"self": {"href": "data/repositories/osrf/cloudsim-legacy.json"}, "html": {"href": "#!/osrf/cloudsim-legacy"}, "avatar": {"href": "data/bytebucket.org/ravatar/{e799e7f6-0caa-464a-97f8-8605a37ebfb1}ts=python"}}, "type": "repository", "name": "cloudsim-legacy", "full_name": "osrf/cloudsim-legacy", "uuid": "{e799e7f6-0caa-464a-97f8-8605a37ebfb1}"}, "branch": {"name": "cloudsim_1.4"}}, "reason": "Already merged", "source": {"commit": {"hash": "6e62721ed176", "type": "commit", "links": {"self": {"href": "data/repositories/osrf/cloudsim-legacy/commit/6e62721ed176.json"}, "html": {"href": "#!/osrf/cloudsim-legacy/commits/6e62721ed176"}}}, "repository": {"links": {"self": {"href": "data/repositories/osrf/cloudsim-legacy.json"}, "html": {"href": "#!/osrf/cloudsim-legacy"}, "avatar": {"href": "data/bytebucket.org/ravatar/{e799e7f6-0caa-464a-97f8-8605a37ebfb1}ts=python"}}, "type": "repository", "name": "cloudsim-legacy", "full_name": "osrf/cloudsim-legacy", "uuid": "{e799e7f6-0caa-464a-97f8-8605a37ebfb1}"}, "branch": {"name": "issue_68"}}, "state": "DECLINED", "author": {"display_name": "Carlos Ag\u00fcero", "uuid": "{da8a8e89-4bb0-421b-bd0e-dbbed3d4ed6a}", "links": {"self": {"href": "https://api.bitbucket.org/2.0/users/%7Bda8a8e89-4bb0-421b-bd0e-dbbed3d4ed6a%7D"}, "html": {"href": "https://bitbucket.org/%7Bda8a8e89-4bb0-421b-bd0e-dbbed3d4ed6a%7D/"}, "avatar": {"href": "data/secure.gravatar.com/avatar/692bf15758111acaddae4da15a47f9e5d=httpsavatar-management--avatars.us-west-2.prod.public.atl-paas.netinitialsCA-0.png"}}, "nickname": "caguero", "type": "user", "account_id": "557058:4ded1ddf-947e-4154-bbd1-3dba24f1bdbd"}, "date": "2013-04-05T21:04:48.741756+00:00"}, "pull_request": {"type": "pullrequest", "id": 32, "links": {"self": {"href": "data/repositories/osrf/cloudsim-legacy/pullrequests/32.json"}, "html": {"href": "#!/osrf/cloudsim-legacy/pull-requests/32"}}, "title": "New administration page"}}, {"approval": {"date": "2013-04-02T21:40:30.577290+00:00", "pullrequest": {"type": "pullrequest", "id": 32, "links": {"self": {"href": "data/repositories/osrf/cloudsim-legacy/pullrequests/32.json"}, "html": {"href": "#!/osrf/cloudsim-legacy/pull-requests/32"}}, "title": "New administration page"}, "user": {"display_name": "Hugo Boyer", "uuid": "{3d87874e-7099-4981-b04f-57f0272faa7d}", "links": {"self": {"href": "https://api.bitbucket.org/2.0/users/%7B3d87874e-7099-4981-b04f-57f0272faa7d%7D"}, "html": {"href": "https://bitbucket.org/%7B3d87874e-7099-4981-b04f-57f0272faa7d%7D/"}, "avatar": {"href": "data/secure.gravatar.com/avatar/21198da8539b599e3633017f5f5f8150d=httpsavatar-management--avatars.us-west-2.prod.public.atl-paas.netinitialsHB-6.png"}}, "nickname": "hugomatic", "type": "user", "account_id": "557058:869c02bb-b246-4cdc-9db3-0064e8add185"}}, "pull_request": {"type": "pullrequest", "id": 32, "links": {"self": {"href": "data/repositories/osrf/cloudsim-legacy/pullrequests/32.json"}, "html": {"href": "#!/osrf/cloudsim-legacy/pull-requests/32"}}, "title": "New administration page"}}, {"comment": {"links": {"self": {"href": "data/repositories/osrf/cloudsim-legacy/pullrequests/32/comments/180498.json"}, "html": {"href": "#!/osrf/cloudsim-legacy/pull-requests/32/_/diff#comment-180498"}}, "deleted": false, "pullrequest": {"type": "pullrequest", "id": 32, "links": {"self": {"href": "data/repositories/osrf/cloudsim-legacy/pullrequests/32.json"}, "html": {"href": "#!/osrf/cloudsim-legacy/pull-requests/32"}}, "title": "New administration page"}, "content": {"raw": "Now that there's a page for admin, we should increase the polling rate for users, from 1500 to 1000 or less.", "markup": "markdown", "html": "<p>Now that there's a page for admin, we should increase the polling rate for users, from 1500 to 1000 or less.</p>", "type": "rendered"}, "created_on": "2013-04-02T21:23:37.539006+00:00", "user": {"display_name": "Hugo Boyer", "uuid": "{3d87874e-7099-4981-b04f-57f0272faa7d}", "links": {"self": {"href": "https://api.bitbucket.org/2.0/users/%7B3d87874e-7099-4981-b04f-57f0272faa7d%7D"}, "html": {"href": "https://bitbucket.org/%7B3d87874e-7099-4981-b04f-57f0272faa7d%7D/"}, "avatar": {"href": "data/secure.gravatar.com/avatar/21198da8539b599e3633017f5f5f8150d=httpsavatar-management--avatars.us-west-2.prod.public.atl-paas.netinitialsHB-6.png"}}, "nickname": "hugomatic", "type": "user", "account_id": "557058:869c02bb-b246-4cdc-9db3-0064e8add185"}, "inline": {}, "updated_on": "2013-04-02T21:23:37.552662+00:00", "type": "pullrequest_comment", "id": 180498}, "pull_request": {"type": "pullrequest", "id": 32, "links": {"self": {"href": "data/repositories/osrf/cloudsim-legacy/pullrequests/32.json"}, "html": {"href": "#!/osrf/cloudsim-legacy/pull-requests/32"}}, "title": "New administration page"}}, {"comment": {"links": {"self": {"href": "data/repositories/osrf/cloudsim-legacy/pullrequests/32/comments/180497.json"}, "html": {"href": "#!/osrf/cloudsim-legacy/pull-requests/32/_/diff#comment-180497"}}, "deleted": false, "pullrequest": {"type": "pullrequest", "id": 32, "links": {"self": {"href": "data/repositories/osrf/cloudsim-legacy/pullrequests/32.json"}, "html": {"href": "#!/osrf/cloudsim-legacy/pull-requests/32"}}, "title": "New administration page"}, "content": {"raw": "Because this is the admin page, the \"admin_only\" div to hide and show parts of the page is not necessary anymore", "markup": "markdown", "html": "<p>Because this is the admin page, the \"admin_only\" div to hide and show parts of the page is not necessary anymore</p>", "type": "rendered"}, "created_on": "2013-04-02T21:22:30.298554+00:00", "user": {"display_name": "Hugo Boyer", "uuid": "{3d87874e-7099-4981-b04f-57f0272faa7d}", "links": {"self": {"href": "https://api.bitbucket.org/2.0/users/%7B3d87874e-7099-4981-b04f-57f0272faa7d%7D"}, "html": {"href": "https://bitbucket.org/%7B3d87874e-7099-4981-b04f-57f0272faa7d%7D/"}, "avatar": {"href": "data/secure.gravatar.com/avatar/21198da8539b599e3633017f5f5f8150d=httpsavatar-management--avatars.us-west-2.prod.public.atl-paas.netinitialsHB-6.png"}}, "nickname": "hugomatic", "type": "user", "account_id": "557058:869c02bb-b246-4cdc-9db3-0064e8add185"}, "inline": {}, "updated_on": "2013-04-02T21:22:30.306252+00:00", "type": "pullrequest_comment", "id": 180497}, "pull_request": {"type": "pullrequest", "id": 32, "links": {"self": {"href": "data/repositories/osrf/cloudsim-legacy/pullrequests/32.json"}, "html": {"href": "#!/osrf/cloudsim-legacy/pull-requests/32"}}, "title": "New administration page"}}, {"comment": {"links": {"self": {"href": "data/repositories/osrf/cloudsim-legacy/pullrequests/32/comments/171422.json"}, "html": {"href": "#!/osrf/cloudsim-legacy/pull-requests/32/_/diff#comment-171422"}}, "deleted": false, "pullrequest": {"type": "pullrequest", "id": 32, "links": {"self": {"href": "data/repositories/osrf/cloudsim-legacy/pullrequests/32.json"}, "html": {"href": "#!/osrf/cloudsim-legacy/pull-requests/32"}}, "title": "New administration page"}, "content": {"raw": "This is not necessary anymore, the user is always \"admin\". The same thing can also be removed from console.py", "markup": "markdown", "html": "<p>This is not necessary anymore, the user is always \"admin\". The same thing can also be removed from console.py</p>", "type": "rendered"}, "created_on": "2013-03-27T02:04:22.515315+00:00", "user": {"display_name": "Hugo Boyer", "uuid": "{3d87874e-7099-4981-b04f-57f0272faa7d}", "links": {"self": {"href": "https://api.bitbucket.org/2.0/users/%7B3d87874e-7099-4981-b04f-57f0272faa7d%7D"}, "html": {"href": "https://bitbucket.org/%7B3d87874e-7099-4981-b04f-57f0272faa7d%7D/"}, "avatar": {"href": "data/secure.gravatar.com/avatar/21198da8539b599e3633017f5f5f8150d=httpsavatar-management--avatars.us-west-2.prod.public.atl-paas.netinitialsHB-6.png"}}, "nickname": "hugomatic", "type": "user", "account_id": "557058:869c02bb-b246-4cdc-9db3-0064e8add185"}, "inline": {}, "updated_on": "2013-03-27T02:04:22.526076+00:00", "type": "pullrequest_comment", "id": 171422}, "pull_request": {"type": "pullrequest", "id": 32, "links": {"self": {"href": "data/repositories/osrf/cloudsim-legacy/pullrequests/32.json"}, "html": {"href": "#!/osrf/cloudsim-legacy/pull-requests/32"}}, "title": "New administration page"}}, {"comment": {"links": {"self": {"href": "data/repositories/osrf/cloudsim-legacy/pullrequests/32/comments/171421.json"}, "html": {"href": "#!/osrf/cloudsim-legacy/pull-requests/32/_/diff#comment-171421"}}, "deleted": false, "pullrequest": {"type": "pullrequest", "id": 32, "links": {"self": {"href": "data/repositories/osrf/cloudsim-legacy/pullrequests/32.json"}, "html": {"href": "#!/osrf/cloudsim-legacy/pull-requests/32"}}, "title": "New administration page"}, "content": {"raw": "\n\n\nthe role should be checked here, so that non admin users can't see the page (at all).... with something like this:     \n      \n\n```\n#!python\n\n        print_http_header()\n        print(\"<title>Access Denied</title>\")\n        print(\"<h1>Access Denied</h1>\")\n        \n        print(\"<h2>%s</h2>\" % e)\n        print(\"Try <a href=\\\"/cloudsim/inside/cgi-bin/logout\\\">logging out</a>.  For assistance, contact <a href=mailto:%s>%s</a>\"%(ADMIN_EMAIL, ADMIN_EMAIL))\n        exit(0)     \n```\n ", "markup": "markdown", "html": "<p>the role should be checked here, so that non admin users can't see the page (at all).... with something like this:     </p>\n<div class=\"codehilite language-python\"><pre><span></span>        <span class=\"n\">print_http_header</span><span class=\"p\">()</span>\n        <span class=\"k\">print</span><span class=\"p\">(</span><span class=\"s2\">&quot;&lt;title&gt;Access Denied&lt;/title&gt;&quot;</span><span class=\"p\">)</span>\n        <span class=\"k\">print</span><span class=\"p\">(</span><span class=\"s2\">&quot;&lt;h1&gt;Access Denied&lt;/h1&gt;&quot;</span><span class=\"p\">)</span>\n\n        <span class=\"k\">print</span><span class=\"p\">(</span><span class=\"s2\">&quot;&lt;h2&gt;</span><span class=\"si\">%s</span><span class=\"s2\">&lt;/h2&gt;&quot;</span> <span class=\"o\">%</span> <span class=\"n\">e</span><span class=\"p\">)</span>\n        <span class=\"k\">print</span><span class=\"p\">(</span><span class=\"s2\">&quot;Try &lt;a href=</span><span class=\"se\">\\&quot;</span><span class=\"s2\">/cloudsim/inside/cgi-bin/logout</span><span class=\"se\">\\&quot;</span><span class=\"s2\">&gt;logging out&lt;/a&gt;.  For assistance, contact &lt;a href=mailto:</span><span class=\"si\">%s</span><span class=\"s2\">&gt;</span><span class=\"si\">%s</span><span class=\"s2\">&lt;/a&gt;&quot;</span><span class=\"o\">%</span><span class=\"p\">(</span><span class=\"n\">ADMIN_EMAIL</span><span class=\"p\">,</span> <span class=\"n\">ADMIN_EMAIL</span><span class=\"p\">))</span>\n        <span class=\"nb\">exit</span><span class=\"p\">(</span><span class=\"mi\">0</span><span class=\"p\">)</span>     \n</pre></div>", "type": "rendered"}, "created_on": "2013-03-27T02:03:00.818196+00:00", "user": {"display_name": "Hugo Boyer", "uuid": "{3d87874e-7099-4981-b04f-57f0272faa7d}", "links": {"self": {"href": "https://api.bitbucket.org/2.0/users/%7B3d87874e-7099-4981-b04f-57f0272faa7d%7D"}, "html": {"href": "https://bitbucket.org/%7B3d87874e-7099-4981-b04f-57f0272faa7d%7D/"}, "avatar": {"href": "data/secure.gravatar.com/avatar/21198da8539b599e3633017f5f5f8150d=httpsavatar-management--avatars.us-west-2.prod.public.atl-paas.netinitialsHB-6.png"}}, "nickname": "hugomatic", "type": "user", "account_id": "557058:869c02bb-b246-4cdc-9db3-0064e8add185"}, "inline": {}, "updated_on": "2013-03-27T02:03:28.791159+00:00", "type": "pullrequest_comment", "id": 171421}, "pull_request": {"type": "pullrequest", "id": 32, "links": {"self": {"href": "data/repositories/osrf/cloudsim-legacy/pullrequests/32.json"}, "html": {"href": "#!/osrf/cloudsim-legacy/pull-requests/32"}}, "title": "New administration page"}}, {"update": {"description": "AWS credentials and user management has been moved to an admin page", "title": "New administration page", "destination": {"commit": {"hash": "ecc7c5800779", "type": "commit", "links": {"self": {"href": "data/repositories/osrf/cloudsim-legacy/commit/ecc7c5800779.json"}, "html": {"href": "#!/osrf/cloudsim-legacy/commits/ecc7c5800779"}}}, "repository": {"links": {"self": {"href": "data/repositories/osrf/cloudsim-legacy.json"}, "html": {"href": "#!/osrf/cloudsim-legacy"}, "avatar": {"href": "data/bytebucket.org/ravatar/{e799e7f6-0caa-464a-97f8-8605a37ebfb1}ts=python"}}, "type": "repository", "name": "cloudsim-legacy", "full_name": "osrf/cloudsim-legacy", "uuid": "{e799e7f6-0caa-464a-97f8-8605a37ebfb1}"}, "branch": {"name": "cloudsim_1.4"}}, "reason": "", "source": {"commit": {"hash": "6e62721ed176", "type": "commit", "links": {"self": {"href": "data/repositories/osrf/cloudsim-legacy/commit/6e62721ed176.json"}, "html": {"href": "#!/osrf/cloudsim-legacy/commits/6e62721ed176"}}}, "repository": {"links": {"self": {"href": "data/repositories/osrf/cloudsim-legacy.json"}, "html": {"href": "#!/osrf/cloudsim-legacy"}, "avatar": {"href": "data/bytebucket.org/ravatar/{e799e7f6-0caa-464a-97f8-8605a37ebfb1}ts=python"}}, "type": "repository", "name": "cloudsim-legacy", "full_name": "osrf/cloudsim-legacy", "uuid": "{e799e7f6-0caa-464a-97f8-8605a37ebfb1}"}, "branch": {"name": "issue_68"}}, "state": "OPEN", "author": {"display_name": "Carlos Ag\u00fcero", "uuid": "{da8a8e89-4bb0-421b-bd0e-dbbed3d4ed6a}", "links": {"self": {"href": "https://api.bitbucket.org/2.0/users/%7Bda8a8e89-4bb0-421b-bd0e-dbbed3d4ed6a%7D"}, "html": {"href": "https://bitbucket.org/%7Bda8a8e89-4bb0-421b-bd0e-dbbed3d4ed6a%7D/"}, "avatar": {"href": "data/secure.gravatar.com/avatar/692bf15758111acaddae4da15a47f9e5d=httpsavatar-management--avatars.us-west-2.prod.public.atl-paas.netinitialsCA-0.png"}}, "nickname": "caguero", "type": "user", "account_id": "557058:4ded1ddf-947e-4154-bbd1-3dba24f1bdbd"}, "date": "2013-03-26T00:56:23.819322+00:00"}, "pull_request": {"type": "pullrequest", "id": 32, "links": {"self": {"href": "data/repositories/osrf/cloudsim-legacy/pullrequests/32.json"}, "html": {"href": "#!/osrf/cloudsim-legacy/pull-requests/32"}}, "title": "New administration page"}}, {"update": {"description": "AWS credentials and user management has been moved to an admin page", "title": "New administration page", "destination": {"commit": {"hash": "ecc7c5800779", "type": "commit", "links": {"self": {"href": "data/repositories/osrf/cloudsim-legacy/commit/ecc7c5800779.json"}, "html": {"href": "#!/osrf/cloudsim-legacy/commits/ecc7c5800779"}}}, "repository": {"links": {"self": {"href": "data/repositories/osrf/cloudsim-legacy.json"}, "html": {"href": "#!/osrf/cloudsim-legacy"}, "avatar": {"href": "data/bytebucket.org/ravatar/{e799e7f6-0caa-464a-97f8-8605a37ebfb1}ts=python"}}, "type": "repository", "name": "cloudsim-legacy", "full_name": "osrf/cloudsim-legacy", "uuid": "{e799e7f6-0caa-464a-97f8-8605a37ebfb1}"}, "branch": {"name": "cloudsim_1.4"}}, "reason": "", "source": {"commit": {"hash": "6e62721ed176", "type": "commit", "links": {"self": {"href": "data/repositories/osrf/cloudsim-legacy/commit/6e62721ed176.json"}, "html": {"href": "#!/osrf/cloudsim-legacy/commits/6e62721ed176"}}}, "repository": {"links": {"self": {"href": "data/repositories/osrf/cloudsim-legacy.json"}, "html": {"href": "#!/osrf/cloudsim-legacy"}, "avatar": {"href": "data/bytebucket.org/ravatar/{e799e7f6-0caa-464a-97f8-8605a37ebfb1}ts=python"}}, "type": "repository", "name": "cloudsim-legacy", "full_name": "osrf/cloudsim-legacy", "uuid": "{e799e7f6-0caa-464a-97f8-8605a37ebfb1}"}, "branch": {"name": "issue_68"}}, "state": "OPEN", "author": {"display_name": "Carlos Ag\u00fcero", "uuid": "{da8a8e89-4bb0-421b-bd0e-dbbed3d4ed6a}", "links": {"self": {"href": "https://api.bitbucket.org/2.0/users/%7Bda8a8e89-4bb0-421b-bd0e-dbbed3d4ed6a%7D"}, "html": {"href": "https://bitbucket.org/%7Bda8a8e89-4bb0-421b-bd0e-dbbed3d4ed6a%7D/"}, "avatar": {"href": "data/secure.gravatar.com/avatar/692bf15758111acaddae4da15a47f9e5d=httpsavatar-management--avatars.us-west-2.prod.public.atl-paas.netinitialsCA-0.png"}}, "nickname": "caguero", "type": "user", "account_id": "557058:4ded1ddf-947e-4154-bbd1-3dba24f1bdbd"}, "date": "2013-03-26T00:56:23.739026+00:00"}, "pull_request": {"type": "pullrequest", "id": 32, "links": {"self": {"href": "data/repositories/osrf/cloudsim-legacy/pullrequests/32.json"}, "html": {"href": "#!/osrf/cloudsim-legacy/pull-requests/32"}}, "title": "New administration page"}}]}