{"pagelen": 50, "values": [{"update": {"description": "Added new projects", "title": "keys and machine types", "destination": {"commit": {"hash": "594e1bcff107", "type": "commit", "links": {"self": {"href": "data/repositories/osrf/cloudsim/commit/594e1bcff107.json"}, "html": {"href": "#!/osrf/cloudsim/commits/594e1bcff107"}}}, "repository": {"links": {"self": {"href": "data/repositories/osrf/cloudsim.json"}, "html": {"href": "#!/osrf/cloudsim"}, "avatar": {"href": "data/bytebucket.org/ravatar/{5f891f62-80d7-4c6b-b39b-41fe459fdda9}ts=default"}}, "type": "repository", "name": "cloudsim", "full_name": "osrf/cloudsim", "uuid": "{5f891f62-80d7-4c6b-b39b-41fe459fdda9}"}, "branch": {"name": "default"}}, "reason": "", "source": {"commit": {"hash": "4cb87c9186ee", "type": "commit", "links": {"self": {"href": "data/repositories/osrf/cloudsim/commit/4cb87c9186ee.json"}, "html": {"href": "#!/osrf/cloudsim/commits/4cb87c9186ee"}}}, "repository": {"links": {"self": {"href": "data/repositories/osrf/cloudsim.json"}, "html": {"href": "#!/osrf/cloudsim"}, "avatar": {"href": "data/bytebucket.org/ravatar/{5f891f62-80d7-4c6b-b39b-41fe459fdda9}ts=default"}}, "type": "repository", "name": "cloudsim", "full_name": "osrf/cloudsim", "uuid": "{5f891f62-80d7-4c6b-b39b-41fe459fdda9}"}, "branch": {"name": "keys and machine types"}}, "state": "MERGED", "author": {"display_name": "Hugo Boyer", "uuid": "{3d87874e-7099-4981-b04f-57f0272faa7d}", "links": {"self": {"href": "https://api.bitbucket.org/2.0/users/%7B3d87874e-7099-4981-b04f-57f0272faa7d%7D"}, "html": {"href": "https://bitbucket.org/%7B3d87874e-7099-4981-b04f-57f0272faa7d%7D/"}, "avatar": {"href": "data/secure.gravatar.com/avatar/21198da8539b599e3633017f5f5f8150d=httpsavatar-management--avatars.us-west-2.prod.public.atl-paas.netinitialsHB-6.png"}}, "nickname": "hugomatic", "type": "user", "account_id": "557058:869c02bb-b246-4cdc-9db3-0064e8add185"}, "date": "2016-09-06T18:30:49.784803+00:00"}, "pull_request": {"type": "pullrequest", "id": 3, "links": {"self": {"href": "data/repositories/osrf/cloudsim/pullrequests/3.json"}, "html": {"href": "#!/osrf/cloudsim/pull-requests/3"}}, "title": "keys and machine types"}}, {"comment": {"links": {"self": {"href": "data/repositories/osrf/cloudsim/pullrequests/3/comments/23351951.json"}, "html": {"href": "#!/osrf/cloudsim/pull-requests/3/_/diff#comment-23351951"}}, "parent": {"id": 23351303, "links": {"self": {"href": "data/repositories/osrf/cloudsim/pullrequests/3/comments/23351303.json"}, "html": {"href": "#!/osrf/cloudsim/pull-requests/3/_/diff#comment-23351303"}}}, "deleted": false, "pullrequest": {"type": "pullrequest", "id": 3, "links": {"self": {"href": "data/repositories/osrf/cloudsim/pullrequests/3.json"}, "html": {"href": "#!/osrf/cloudsim/pull-requests/3"}}, "title": "keys and machine types"}, "content": {"raw": "I thought I was typing a commit message, but it was a branch name instead. Spaces should be avoided.", "markup": "markdown", "html": "<p>I thought I was typing a commit message, but it was a branch name instead. Spaces should be avoided.</p>", "type": "rendered"}, "created_on": "2016-09-06T18:02:04.040852+00:00", "user": {"display_name": "Hugo Boyer", "uuid": "{3d87874e-7099-4981-b04f-57f0272faa7d}", "links": {"self": {"href": "https://api.bitbucket.org/2.0/users/%7B3d87874e-7099-4981-b04f-57f0272faa7d%7D"}, "html": {"href": "https://bitbucket.org/%7B3d87874e-7099-4981-b04f-57f0272faa7d%7D/"}, "avatar": {"href": "data/secure.gravatar.com/avatar/21198da8539b599e3633017f5f5f8150d=httpsavatar-management--avatars.us-west-2.prod.public.atl-paas.netinitialsHB-6.png"}}, "nickname": "hugomatic", "type": "user", "account_id": "557058:869c02bb-b246-4cdc-9db3-0064e8add185"}, "updated_on": "2016-09-06T18:02:04.046774+00:00", "type": "pullrequest_comment", "id": 23351951}, "pull_request": {"type": "pullrequest", "id": 3, "links": {"self": {"href": "data/repositories/osrf/cloudsim/pullrequests/3.json"}, "html": {"href": "#!/osrf/cloudsim/pull-requests/3"}}, "title": "keys and machine types"}}, {"approval": {"date": "2016-09-06T17:57:32.391054+00:00", "pullrequest": {"type": "pullrequest", "id": 3, "links": {"self": {"href": "data/repositories/osrf/cloudsim/pullrequests/3.json"}, "html": {"href": "#!/osrf/cloudsim/pull-requests/3"}}, "title": "keys and machine types"}, "user": {"display_name": "Louise Poubel", "uuid": "{5cfa2075-477b-4ded-bdb9-8d2479544ec4}", "links": {"self": {"href": "https://api.bitbucket.org/2.0/users/%7B5cfa2075-477b-4ded-bdb9-8d2479544ec4%7D"}, "html": {"href": "https://bitbucket.org/%7B5cfa2075-477b-4ded-bdb9-8d2479544ec4%7D/"}, "avatar": {"href": "https://avatar-management--avatars.us-west-2.prod.public.atl-paas.net/557058:6ff86fcb-b7ab-44a5-b8a6-f6d9cae8b6e8/7d903d90-c5ea-4182-b7ef-0d467e9e1c74/128"}}, "nickname": "chapulina", "type": "user", "account_id": "557058:6ff86fcb-b7ab-44a5-b8a6-f6d9cae8b6e8"}}, "pull_request": {"type": "pullrequest", "id": 3, "links": {"self": {"href": "data/repositories/osrf/cloudsim/pullrequests/3.json"}, "html": {"href": "#!/osrf/cloudsim/pull-requests/3"}}, "title": "keys and machine types"}}, {"comment": {"links": {"self": {"href": "data/repositories/osrf/cloudsim/pullrequests/3/comments/23351712.json"}, "html": {"href": "#!/osrf/cloudsim/pull-requests/3/_/diff#comment-23351712"}}, "parent": {"id": 23251845, "links": {"self": {"href": "data/repositories/osrf/cloudsim/pullrequests/3/comments/23251845.json"}, "html": {"href": "#!/osrf/cloudsim/pull-requests/3/_/diff#comment-23251845"}}}, "deleted": false, "pullrequest": {"type": "pullrequest", "id": 3, "links": {"self": {"href": "data/repositories/osrf/cloudsim/pullrequests/3.json"}, "html": {"href": "#!/osrf/cloudsim/pull-requests/3"}}, "title": "keys and machine types"}, "content": {"raw": "Ok. I added a blank page for it:\n\n#!/osrf/cloudsim/wiki/Home", "markup": "markdown", "html": "<p>Ok. I added a blank page for it:</p>\n<p><a href=\"#!/osrf/cloudsim/wiki/Home\" rel=\"nofollow\" class=\"ap-connect-link\">#!/osrf/cloudsim/wiki/Home</a></p>", "type": "rendered"}, "created_on": "2016-09-06T17:56:59.052703+00:00", "user": {"display_name": "Louise Poubel", "uuid": "{5cfa2075-477b-4ded-bdb9-8d2479544ec4}", "links": {"self": {"href": "https://api.bitbucket.org/2.0/users/%7B5cfa2075-477b-4ded-bdb9-8d2479544ec4%7D"}, "html": {"href": "https://bitbucket.org/%7B5cfa2075-477b-4ded-bdb9-8d2479544ec4%7D/"}, "avatar": {"href": "https://avatar-management--avatars.us-west-2.prod.public.atl-paas.net/557058:6ff86fcb-b7ab-44a5-b8a6-f6d9cae8b6e8/7d903d90-c5ea-4182-b7ef-0d467e9e1c74/128"}}, "nickname": "chapulina", "type": "user", "account_id": "557058:6ff86fcb-b7ab-44a5-b8a6-f6d9cae8b6e8"}, "updated_on": "2016-09-06T17:56:59.057959+00:00", "type": "pullrequest_comment", "id": 23351712}, "pull_request": {"type": "pullrequest", "id": 3, "links": {"self": {"href": "data/repositories/osrf/cloudsim/pullrequests/3.json"}, "html": {"href": "#!/osrf/cloudsim/pull-requests/3"}}, "title": "keys and machine types"}}, {"comment": {"links": {"self": {"href": "data/repositories/osrf/cloudsim/pullrequests/3/comments/23351466.json"}, "html": {"href": "#!/osrf/cloudsim/pull-requests/3/_/diff#comment-23351466"}}, "deleted": false, "pullrequest": {"type": "pullrequest", "id": 3, "links": {"self": {"href": "data/repositories/osrf/cloudsim/pullrequests/3.json"}, "html": {"href": "#!/osrf/cloudsim/pull-requests/3"}}, "title": "keys and machine types"}, "content": {"raw": "FYI, all versions are also visible on the [README](#!/osrf/cloudsim/overview) now.", "markup": "markdown", "html": "<p>FYI, all versions are also visible on the <a data-is-external-link=\"true\" href=\"#!/osrf/cloudsim/overview\" rel=\"nofollow\">README</a> now.</p>", "type": "rendered"}, "created_on": "2016-09-06T17:52:07.930273+00:00", "user": {"display_name": "Louise Poubel", "uuid": "{5cfa2075-477b-4ded-bdb9-8d2479544ec4}", "links": {"self": {"href": "https://api.bitbucket.org/2.0/users/%7B5cfa2075-477b-4ded-bdb9-8d2479544ec4%7D"}, "html": {"href": "https://bitbucket.org/%7B5cfa2075-477b-4ded-bdb9-8d2479544ec4%7D/"}, "avatar": {"href": "https://avatar-management--avatars.us-west-2.prod.public.atl-paas.net/557058:6ff86fcb-b7ab-44a5-b8a6-f6d9cae8b6e8/7d903d90-c5ea-4182-b7ef-0d467e9e1c74/128"}}, "nickname": "chapulina", "type": "user", "account_id": "557058:6ff86fcb-b7ab-44a5-b8a6-f6d9cae8b6e8"}, "inline": {}, "updated_on": "2016-09-06T17:52:20.227273+00:00", "type": "pullrequest_comment", "id": 23351466}, "pull_request": {"type": "pullrequest", "id": 3, "links": {"self": {"href": "data/repositories/osrf/cloudsim/pullrequests/3.json"}, "html": {"href": "#!/osrf/cloudsim/pull-requests/3"}}, "title": "keys and machine types"}}, {"update": {"description": "Added new projects", "title": "keys and machine types", "destination": {"commit": {"hash": "594e1bcff107", "type": "commit", "links": {"self": {"href": "data/repositories/osrf/cloudsim/commit/594e1bcff107.json"}, "html": {"href": "#!/osrf/cloudsim/commits/594e1bcff107"}}}, "repository": {"links": {"self": {"href": "data/repositories/osrf/cloudsim.json"}, "html": {"href": "#!/osrf/cloudsim"}, "avatar": {"href": "data/bytebucket.org/ravatar/{5f891f62-80d7-4c6b-b39b-41fe459fdda9}ts=default"}}, "type": "repository", "name": "cloudsim", "full_name": "osrf/cloudsim", "uuid": "{5f891f62-80d7-4c6b-b39b-41fe459fdda9}"}, "branch": {"name": "default"}}, "reason": "", "source": {"commit": {"hash": "4cb87c9186ee", "type": "commit", "links": {"self": {"href": "data/repositories/osrf/cloudsim/commit/4cb87c9186ee.json"}, "html": {"href": "#!/osrf/cloudsim/commits/4cb87c9186ee"}}}, "repository": {"links": {"self": {"href": "data/repositories/osrf/cloudsim.json"}, "html": {"href": "#!/osrf/cloudsim"}, "avatar": {"href": "data/bytebucket.org/ravatar/{5f891f62-80d7-4c6b-b39b-41fe459fdda9}ts=default"}}, "type": "repository", "name": "cloudsim", "full_name": "osrf/cloudsim", "uuid": "{5f891f62-80d7-4c6b-b39b-41fe459fdda9}"}, "branch": {"name": "keys and machine types"}}, "state": "OPEN", "author": {"display_name": "Louise Poubel", "uuid": "{5cfa2075-477b-4ded-bdb9-8d2479544ec4}", "links": {"self": {"href": "https://api.bitbucket.org/2.0/users/%7B5cfa2075-477b-4ded-bdb9-8d2479544ec4%7D"}, "html": {"href": "https://bitbucket.org/%7B5cfa2075-477b-4ded-bdb9-8d2479544ec4%7D/"}, "avatar": {"href": "https://avatar-management--avatars.us-west-2.prod.public.atl-paas.net/557058:6ff86fcb-b7ab-44a5-b8a6-f6d9cae8b6e8/7d903d90-c5ea-4182-b7ef-0d467e9e1c74/128"}}, "nickname": "chapulina", "type": "user", "account_id": "557058:6ff86fcb-b7ab-44a5-b8a6-f6d9cae8b6e8"}, "date": "2016-09-06T17:50:22.293224+00:00"}, "pull_request": {"type": "pullrequest", "id": 3, "links": {"self": {"href": "data/repositories/osrf/cloudsim/pullrequests/3.json"}, "html": {"href": "#!/osrf/cloudsim/pull-requests/3"}}, "title": "keys and machine types"}}, {"comment": {"links": {"self": {"href": "data/repositories/osrf/cloudsim/pullrequests/3/comments/23351303.json"}, "html": {"href": "#!/osrf/cloudsim/pull-requests/3/_/diff#comment-23351303"}}, "deleted": false, "pullrequest": {"type": "pullrequest", "id": 3, "links": {"self": {"href": "data/repositories/osrf/cloudsim/pullrequests/3.json"}, "html": {"href": "#!/osrf/cloudsim/pull-requests/3"}}, "title": "keys and machine types"}, "content": {"raw": "Btw, I had no idea there could be spaces in branch names. mercurial's autocomplete doesn't escape them, so they have to be escaped manually.", "markup": "markdown", "html": "<p>Btw, I had no idea there could be spaces in branch names. mercurial's autocomplete doesn't escape them, so they have to be escaped manually.</p>", "type": "rendered"}, "created_on": "2016-09-06T17:49:18.566257+00:00", "user": {"display_name": "Louise Poubel", "uuid": "{5cfa2075-477b-4ded-bdb9-8d2479544ec4}", "links": {"self": {"href": "https://api.bitbucket.org/2.0/users/%7B5cfa2075-477b-4ded-bdb9-8d2479544ec4%7D"}, "html": {"href": "https://bitbucket.org/%7B5cfa2075-477b-4ded-bdb9-8d2479544ec4%7D/"}, "avatar": {"href": "https://avatar-management--avatars.us-west-2.prod.public.atl-paas.net/557058:6ff86fcb-b7ab-44a5-b8a6-f6d9cae8b6e8/7d903d90-c5ea-4182-b7ef-0d467e9e1c74/128"}}, "nickname": "chapulina", "type": "user", "account_id": "557058:6ff86fcb-b7ab-44a5-b8a6-f6d9cae8b6e8"}, "updated_on": "2016-09-06T17:49:30.782888+00:00", "type": "pullrequest_comment", "id": 23351303}, "pull_request": {"type": "pullrequest", "id": 3, "links": {"self": {"href": "data/repositories/osrf/cloudsim/pullrequests/3.json"}, "html": {"href": "#!/osrf/cloudsim/pull-requests/3"}}, "title": "keys and machine types"}}, {"update": {"description": "Added new projects", "title": "keys and machine types", "destination": {"commit": {"hash": "71ec555b97b3", "type": "commit", "links": {"self": {"href": "data/repositories/osrf/cloudsim/commit/71ec555b97b3.json"}, "html": {"href": "#!/osrf/cloudsim/commits/71ec555b97b3"}}}, "repository": {"links": {"self": {"href": "data/repositories/osrf/cloudsim.json"}, "html": {"href": "#!/osrf/cloudsim"}, "avatar": {"href": "data/bytebucket.org/ravatar/{5f891f62-80d7-4c6b-b39b-41fe459fdda9}ts=default"}}, "type": "repository", "name": "cloudsim", "full_name": "osrf/cloudsim", "uuid": "{5f891f62-80d7-4c6b-b39b-41fe459fdda9}"}, "branch": {"name": "default"}}, "reason": "", "source": {"commit": {"hash": "b5f00d1825b5", "type": "commit", "links": {"self": {"href": "data/repositories/osrf/cloudsim/commit/b5f00d1825b5.json"}, "html": {"href": "#!/osrf/cloudsim/commits/b5f00d1825b5"}}}, "repository": {"links": {"self": {"href": "data/repositories/osrf/cloudsim.json"}, "html": {"href": "#!/osrf/cloudsim"}, "avatar": {"href": "data/bytebucket.org/ravatar/{5f891f62-80d7-4c6b-b39b-41fe459fdda9}ts=default"}}, "type": "repository", "name": "cloudsim", "full_name": "osrf/cloudsim", "uuid": "{5f891f62-80d7-4c6b-b39b-41fe459fdda9}"}, "branch": {"name": "keys and machine types"}}, "state": "OPEN", "author": {"display_name": "Hugo Boyer", "uuid": "{3d87874e-7099-4981-b04f-57f0272faa7d}", "links": {"self": {"href": "https://api.bitbucket.org/2.0/users/%7B3d87874e-7099-4981-b04f-57f0272faa7d%7D"}, "html": {"href": "https://bitbucket.org/%7B3d87874e-7099-4981-b04f-57f0272faa7d%7D/"}, "avatar": {"href": "data/secure.gravatar.com/avatar/21198da8539b599e3633017f5f5f8150d=httpsavatar-management--avatars.us-west-2.prod.public.atl-paas.netinitialsHB-6.png"}}, "nickname": "hugomatic", "type": "user", "account_id": "557058:869c02bb-b246-4cdc-9db3-0064e8add185"}, "date": "2016-09-03T02:34:30.513199+00:00"}, "pull_request": {"type": "pullrequest", "id": 3, "links": {"self": {"href": "data/repositories/osrf/cloudsim/pullrequests/3.json"}, "html": {"href": "#!/osrf/cloudsim/pull-requests/3"}}, "title": "keys and machine types"}}, {"comment": {"links": {"self": {"href": "data/repositories/osrf/cloudsim/pullrequests/3/comments/23251845.json"}, "html": {"href": "#!/osrf/cloudsim/pull-requests/3/_/diff#comment-23251845"}}, "parent": {"id": 23196297, "links": {"self": {"href": "data/repositories/osrf/cloudsim/pullrequests/3/comments/23196297.json"}, "html": {"href": "#!/osrf/cloudsim/pull-requests/3/_/diff#comment-23196297"}}}, "deleted": false, "pullrequest": {"type": "pullrequest", "id": 3, "links": {"self": {"href": "data/repositories/osrf/cloudsim/pullrequests/3.json"}, "html": {"href": "#!/osrf/cloudsim/pull-requests/3"}}, "title": "keys and machine types"}, "content": {"raw": "I'll add it when the server serves keys. Right now, it only serves machine types and those are going away\n", "markup": "markdown", "html": "<p>I'll add it when the server serves keys. Right now, it only serves machine types and those are going away</p>", "type": "rendered"}, "created_on": "2016-09-03T02:34:21.937795+00:00", "user": {"display_name": "Hugo Boyer", "uuid": "{3d87874e-7099-4981-b04f-57f0272faa7d}", "links": {"self": {"href": "https://api.bitbucket.org/2.0/users/%7B3d87874e-7099-4981-b04f-57f0272faa7d%7D"}, "html": {"href": "https://bitbucket.org/%7B3d87874e-7099-4981-b04f-57f0272faa7d%7D/"}, "avatar": {"href": "data/secure.gravatar.com/avatar/21198da8539b599e3633017f5f5f8150d=httpsavatar-management--avatars.us-west-2.prod.public.atl-paas.netinitialsHB-6.png"}}, "nickname": "hugomatic", "type": "user", "account_id": "557058:869c02bb-b246-4cdc-9db3-0064e8add185"}, "updated_on": "2016-09-03T02:34:21.942709+00:00", "type": "pullrequest_comment", "id": 23251845}, "pull_request": {"type": "pullrequest", "id": 3, "links": {"self": {"href": "data/repositories/osrf/cloudsim/pullrequests/3.json"}, "html": {"href": "#!/osrf/cloudsim/pull-requests/3"}}, "title": "keys and machine types"}}, {"comment": {"links": {"self": {"href": "data/repositories/osrf/cloudsim/pullrequests/3/comments/23251841.json"}, "html": {"href": "#!/osrf/cloudsim/pull-requests/3/_/diff#comment-23251841"}}, "parent": {"id": 23196375, "links": {"self": {"href": "data/repositories/osrf/cloudsim/pullrequests/3/comments/23196375.json"}, "html": {"href": "#!/osrf/cloudsim/pull-requests/3/_/diff#comment-23196375"}}}, "deleted": false, "pullrequest": {"type": "pullrequest", "id": 3, "links": {"self": {"href": "data/repositories/osrf/cloudsim/pullrequests/3.json"}, "html": {"href": "#!/osrf/cloudsim/pull-requests/3"}}, "title": "keys and machine types"}, "content": {"raw": "done", "markup": "markdown", "html": "<p>done</p>", "type": "rendered"}, "created_on": "2016-09-03T02:33:25.010305+00:00", "user": {"display_name": "Hugo Boyer", "uuid": "{3d87874e-7099-4981-b04f-57f0272faa7d}", "links": {"self": {"href": "https://api.bitbucket.org/2.0/users/%7B3d87874e-7099-4981-b04f-57f0272faa7d%7D"}, "html": {"href": "https://bitbucket.org/%7B3d87874e-7099-4981-b04f-57f0272faa7d%7D/"}, "avatar": {"href": "data/secure.gravatar.com/avatar/21198da8539b599e3633017f5f5f8150d=httpsavatar-management--avatars.us-west-2.prod.public.atl-paas.netinitialsHB-6.png"}}, "nickname": "hugomatic", "type": "user", "account_id": "557058:869c02bb-b246-4cdc-9db3-0064e8add185"}, "updated_on": "2016-09-03T02:33:25.015687+00:00", "type": "pullrequest_comment", "id": 23251841}, "pull_request": {"type": "pullrequest", "id": 3, "links": {"self": {"href": "data/repositories/osrf/cloudsim/pullrequests/3.json"}, "html": {"href": "#!/osrf/cloudsim/pull-requests/3"}}, "title": "keys and machine types"}}, {"comment": {"links": {"self": {"href": "data/repositories/osrf/cloudsim/pullrequests/3/comments/23251825.json"}, "html": {"href": "#!/osrf/cloudsim/pull-requests/3/_/diff#comment-23251825"}}, "parent": {"id": 23196476, "links": {"self": {"href": "data/repositories/osrf/cloudsim/pullrequests/3/comments/23196476.json"}, "html": {"href": "#!/osrf/cloudsim/pull-requests/3/_/diff#comment-23196476"}}}, "deleted": false, "pullrequest": {"type": "pullrequest", "id": 3, "links": {"self": {"href": "data/repositories/osrf/cloudsim/pullrequests/3.json"}, "html": {"href": "#!/osrf/cloudsim/pull-requests/3"}}, "title": "keys and machine types"}, "content": {"raw": "No, its in build.bash, which calls npm_use_links", "markup": "markdown", "html": "<p>No, its in build.bash, which calls npm_use_links</p>", "type": "rendered"}, "created_on": "2016-09-03T02:26:34.661109+00:00", "user": {"display_name": "Hugo Boyer", "uuid": "{3d87874e-7099-4981-b04f-57f0272faa7d}", "links": {"self": {"href": "https://api.bitbucket.org/2.0/users/%7B3d87874e-7099-4981-b04f-57f0272faa7d%7D"}, "html": {"href": "https://bitbucket.org/%7B3d87874e-7099-4981-b04f-57f0272faa7d%7D/"}, "avatar": {"href": "data/secure.gravatar.com/avatar/21198da8539b599e3633017f5f5f8150d=httpsavatar-management--avatars.us-west-2.prod.public.atl-paas.netinitialsHB-6.png"}}, "nickname": "hugomatic", "type": "user", "account_id": "557058:869c02bb-b246-4cdc-9db3-0064e8add185"}, "updated_on": "2016-09-03T02:26:34.667212+00:00", "type": "pullrequest_comment", "id": 23251825}, "pull_request": {"type": "pullrequest", "id": 3, "links": {"self": {"href": "data/repositories/osrf/cloudsim/pullrequests/3.json"}, "html": {"href": "#!/osrf/cloudsim/pull-requests/3"}}, "title": "keys and machine types"}}, {"comment": {"links": {"self": {"href": "data/repositories/osrf/cloudsim/pullrequests/3/comments/23251597.json"}, "html": {"href": "#!/osrf/cloudsim/pull-requests/3/_/diff#comment-23251597"}}, "parent": {"id": 23196505, "links": {"self": {"href": "data/repositories/osrf/cloudsim/pullrequests/3/comments/23196505.json"}, "html": {"href": "#!/osrf/cloudsim/pull-requests/3/_/diff#comment-23196505"}}}, "deleted": false, "pullrequest": {"type": "pullrequest", "id": 3, "links": {"self": {"href": "data/repositories/osrf/cloudsim/pullrequests/3.json"}, "html": {"href": "#!/osrf/cloudsim/pull-requests/3"}}, "title": "keys and machine types"}, "content": {"raw": "fixed", "markup": "markdown", "html": "<p>fixed</p>", "type": "rendered"}, "created_on": "2016-09-03T01:25:21.008695+00:00", "user": {"display_name": "Hugo Boyer", "uuid": "{3d87874e-7099-4981-b04f-57f0272faa7d}", "links": {"self": {"href": "https://api.bitbucket.org/2.0/users/%7B3d87874e-7099-4981-b04f-57f0272faa7d%7D"}, "html": {"href": "https://bitbucket.org/%7B3d87874e-7099-4981-b04f-57f0272faa7d%7D/"}, "avatar": {"href": "data/secure.gravatar.com/avatar/21198da8539b599e3633017f5f5f8150d=httpsavatar-management--avatars.us-west-2.prod.public.atl-paas.netinitialsHB-6.png"}}, "nickname": "hugomatic", "type": "user", "account_id": "557058:869c02bb-b246-4cdc-9db3-0064e8add185"}, "updated_on": "2016-09-03T01:25:21.013426+00:00", "type": "pullrequest_comment", "id": 23251597}, "pull_request": {"type": "pullrequest", "id": 3, "links": {"self": {"href": "data/repositories/osrf/cloudsim/pullrequests/3.json"}, "html": {"href": "#!/osrf/cloudsim/pull-requests/3"}}, "title": "keys and machine types"}}, {"update": {"description": "Added new projects", "title": "keys and machine types", "destination": {"commit": {"hash": "94fcab407d62", "type": "commit", "links": {"self": {"href": "data/repositories/osrf/cloudsim/commit/94fcab407d62.json"}, "html": {"href": "#!/osrf/cloudsim/commits/94fcab407d62"}}}, "repository": {"links": {"self": {"href": "data/repositories/osrf/cloudsim.json"}, "html": {"href": "#!/osrf/cloudsim"}, "avatar": {"href": "data/bytebucket.org/ravatar/{5f891f62-80d7-4c6b-b39b-41fe459fdda9}ts=default"}}, "type": "repository", "name": "cloudsim", "full_name": "osrf/cloudsim", "uuid": "{5f891f62-80d7-4c6b-b39b-41fe459fdda9}"}, "branch": {"name": "default"}}, "reason": "", "source": {"commit": {"hash": "27ea69f26a72", "type": "commit", "links": {"self": {"href": "data/repositories/osrf/cloudsim/commit/27ea69f26a72.json"}, "html": {"href": "#!/osrf/cloudsim/commits/27ea69f26a72"}}}, "repository": {"links": {"self": {"href": "data/repositories/osrf/cloudsim.json"}, "html": {"href": "#!/osrf/cloudsim"}, "avatar": {"href": "data/bytebucket.org/ravatar/{5f891f62-80d7-4c6b-b39b-41fe459fdda9}ts=default"}}, "type": "repository", "name": "cloudsim", "full_name": "osrf/cloudsim", "uuid": "{5f891f62-80d7-4c6b-b39b-41fe459fdda9}"}, "branch": {"name": "keys and machine types"}}, "state": "OPEN", "author": {"display_name": "Hugo Boyer", "uuid": "{3d87874e-7099-4981-b04f-57f0272faa7d}", "links": {"self": {"href": "https://api.bitbucket.org/2.0/users/%7B3d87874e-7099-4981-b04f-57f0272faa7d%7D"}, "html": {"href": "https://bitbucket.org/%7B3d87874e-7099-4981-b04f-57f0272faa7d%7D/"}, "avatar": {"href": "data/secure.gravatar.com/avatar/21198da8539b599e3633017f5f5f8150d=httpsavatar-management--avatars.us-west-2.prod.public.atl-paas.netinitialsHB-6.png"}}, "nickname": "hugomatic", "type": "user", "account_id": "557058:869c02bb-b246-4cdc-9db3-0064e8add185"}, "date": "2016-09-02T21:42:39.966218+00:00"}, "pull_request": {"type": "pullrequest", "id": 3, "links": {"self": {"href": "data/repositories/osrf/cloudsim/pullrequests/3.json"}, "html": {"href": "#!/osrf/cloudsim/pull-requests/3"}}, "title": "keys and machine types"}}, {"comment": {"links": {"self": {"href": "data/repositories/osrf/cloudsim/pullrequests/3/comments/23196505.json"}, "html": {"href": "#!/osrf/cloudsim/pull-requests/3/_/diff#comment-23196505"}}, "deleted": false, "pullrequest": {"type": "pullrequest", "id": 3, "links": {"self": {"href": "data/repositories/osrf/cloudsim/pullrequests/3.json"}, "html": {"href": "#!/osrf/cloudsim/pull-requests/3"}}, "title": "keys and machine types"}, "content": {"raw": "How about `gz-machinetypes`, doesn't it need to be in `bower_create_links` and such?", "markup": "markdown", "html": "<p>How about <code>gz-machinetypes</code>, doesn't it need to be in <code>bower_create_links</code> and such?</p>", "type": "rendered"}, "created_on": "2016-09-01T23:32:32.689551+00:00", "user": {"display_name": "Louise Poubel", "uuid": "{5cfa2075-477b-4ded-bdb9-8d2479544ec4}", "links": {"self": {"href": "https://api.bitbucket.org/2.0/users/%7B5cfa2075-477b-4ded-bdb9-8d2479544ec4%7D"}, "html": {"href": "https://bitbucket.org/%7B5cfa2075-477b-4ded-bdb9-8d2479544ec4%7D/"}, "avatar": {"href": "https://avatar-management--avatars.us-west-2.prod.public.atl-paas.net/557058:6ff86fcb-b7ab-44a5-b8a6-f6d9cae8b6e8/7d903d90-c5ea-4182-b7ef-0d467e9e1c74/128"}}, "nickname": "chapulina", "type": "user", "account_id": "557058:6ff86fcb-b7ab-44a5-b8a6-f6d9cae8b6e8"}, "updated_on": "2016-09-01T23:32:32.692550+00:00", "type": "pullrequest_comment", "id": 23196505}, "pull_request": {"type": "pullrequest", "id": 3, "links": {"self": {"href": "data/repositories/osrf/cloudsim/pullrequests/3.json"}, "html": {"href": "#!/osrf/cloudsim/pull-requests/3"}}, "title": "keys and machine types"}}, {"comment": {"links": {"self": {"href": "data/repositories/osrf/cloudsim/pullrequests/3/comments/23196476.json"}, "html": {"href": "#!/osrf/cloudsim/pull-requests/3/_/diff#comment-23196476"}}, "deleted": false, "pullrequest": {"type": "pullrequest", "id": 3, "links": {"self": {"href": "data/repositories/osrf/cloudsim/pullrequests/3.json"}, "html": {"href": "#!/osrf/cloudsim/pull-requests/3"}}, "title": "keys and machine types"}, "content": {"raw": "What will `cloudsim-keys` be linked to? Does it need to be in `npm_create_links` and `npm_use_links`?", "markup": "markdown", "html": "<p>What will <code>cloudsim-keys</code> be linked to? Does it need to be in <code>npm_create_links</code> and <code>npm_use_links</code>?</p>", "type": "rendered"}, "created_on": "2016-09-01T23:31:16.877747+00:00", "user": {"display_name": "Louise Poubel", "uuid": "{5cfa2075-477b-4ded-bdb9-8d2479544ec4}", "links": {"self": {"href": "https://api.bitbucket.org/2.0/users/%7B5cfa2075-477b-4ded-bdb9-8d2479544ec4%7D"}, "html": {"href": "https://bitbucket.org/%7B5cfa2075-477b-4ded-bdb9-8d2479544ec4%7D/"}, "avatar": {"href": "https://avatar-management--avatars.us-west-2.prod.public.atl-paas.net/557058:6ff86fcb-b7ab-44a5-b8a6-f6d9cae8b6e8/7d903d90-c5ea-4182-b7ef-0d467e9e1c74/128"}}, "nickname": "chapulina", "type": "user", "account_id": "557058:6ff86fcb-b7ab-44a5-b8a6-f6d9cae8b6e8"}, "updated_on": "2016-09-01T23:31:16.879721+00:00", "type": "pullrequest_comment", "id": 23196476}, "pull_request": {"type": "pullrequest", "id": 3, "links": {"self": {"href": "data/repositories/osrf/cloudsim/pullrequests/3.json"}, "html": {"href": "#!/osrf/cloudsim/pull-requests/3"}}, "title": "keys and machine types"}}, {"comment": {"links": {"self": {"href": "data/repositories/osrf/cloudsim/pullrequests/3/comments/23196375.json"}, "html": {"href": "#!/osrf/cloudsim/pull-requests/3/_/diff#comment-23196375"}}, "deleted": false, "pullrequest": {"type": "pullrequest", "id": 3, "links": {"self": {"href": "data/repositories/osrf/cloudsim/pullrequests/3.json"}, "html": {"href": "#!/osrf/cloudsim/pull-requests/3"}}, "title": "keys and machine types"}, "content": {"raw": "Also please add their codeship statuses to README.", "markup": "markdown", "html": "<p>Also please add their codeship statuses to README.</p>", "type": "rendered"}, "created_on": "2016-09-01T23:27:04.049481+00:00", "user": {"display_name": "Louise Poubel", "uuid": "{5cfa2075-477b-4ded-bdb9-8d2479544ec4}", "links": {"self": {"href": "https://api.bitbucket.org/2.0/users/%7B5cfa2075-477b-4ded-bdb9-8d2479544ec4%7D"}, "html": {"href": "https://bitbucket.org/%7B5cfa2075-477b-4ded-bdb9-8d2479544ec4%7D/"}, "avatar": {"href": "https://avatar-management--avatars.us-west-2.prod.public.atl-paas.net/557058:6ff86fcb-b7ab-44a5-b8a6-f6d9cae8b6e8/7d903d90-c5ea-4182-b7ef-0d467e9e1c74/128"}}, "nickname": "chapulina", "type": "user", "account_id": "557058:6ff86fcb-b7ab-44a5-b8a6-f6d9cae8b6e8"}, "updated_on": "2016-09-01T23:27:04.053691+00:00", "type": "pullrequest_comment", "id": 23196375}, "pull_request": {"type": "pullrequest", "id": 3, "links": {"self": {"href": "data/repositories/osrf/cloudsim/pullrequests/3.json"}, "html": {"href": "#!/osrf/cloudsim/pull-requests/3"}}, "title": "keys and machine types"}}, {"comment": {"links": {"self": {"href": "data/repositories/osrf/cloudsim/pullrequests/3/comments/23196297.json"}, "html": {"href": "#!/osrf/cloudsim/pull-requests/3/_/diff#comment-23196297"}}, "deleted": false, "pullrequest": {"type": "pullrequest", "id": 3, "links": {"self": {"href": "data/repositories/osrf/cloudsim/pullrequests/3.json"}, "html": {"href": "#!/osrf/cloudsim/pull-requests/3"}}, "title": "keys and machine types"}, "content": {"raw": "Do you mind adding documentation about them to the wiki?", "markup": "markdown", "html": "<p>Do you mind adding documentation about them to the wiki?</p>", "type": "rendered"}, "created_on": "2016-09-01T23:23:18.403055+00:00", "user": {"display_name": "Louise Poubel", "uuid": "{5cfa2075-477b-4ded-bdb9-8d2479544ec4}", "links": {"self": {"href": "https://api.bitbucket.org/2.0/users/%7B5cfa2075-477b-4ded-bdb9-8d2479544ec4%7D"}, "html": {"href": "https://bitbucket.org/%7B5cfa2075-477b-4ded-bdb9-8d2479544ec4%7D/"}, "avatar": {"href": "https://avatar-management--avatars.us-west-2.prod.public.atl-paas.net/557058:6ff86fcb-b7ab-44a5-b8a6-f6d9cae8b6e8/7d903d90-c5ea-4182-b7ef-0d467e9e1c74/128"}}, "nickname": "chapulina", "type": "user", "account_id": "557058:6ff86fcb-b7ab-44a5-b8a6-f6d9cae8b6e8"}, "updated_on": "2016-09-01T23:23:18.404803+00:00", "type": "pullrequest_comment", "id": 23196297}, "pull_request": {"type": "pullrequest", "id": 3, "links": {"self": {"href": "data/repositories/osrf/cloudsim/pullrequests/3.json"}, "html": {"href": "#!/osrf/cloudsim/pull-requests/3"}}, "title": "keys and machine types"}}, {"update": {"description": "Added new projects", "title": "keys and machine types", "destination": {"commit": {"hash": "94fcab407d62", "type": "commit", "links": {"self": {"href": "data/repositories/osrf/cloudsim/commit/94fcab407d62.json"}, "html": {"href": "#!/osrf/cloudsim/commits/94fcab407d62"}}}, "repository": {"links": {"self": {"href": "data/repositories/osrf/cloudsim.json"}, "html": {"href": "#!/osrf/cloudsim"}, "avatar": {"href": "data/bytebucket.org/ravatar/{5f891f62-80d7-4c6b-b39b-41fe459fdda9}ts=default"}}, "type": "repository", "name": "cloudsim", "full_name": "osrf/cloudsim", "uuid": "{5f891f62-80d7-4c6b-b39b-41fe459fdda9}"}, "branch": {"name": "default"}}, "reason": "", "source": {"commit": {"hash": "5601ae82a4a3", "type": "commit", "links": {"self": {"href": "data/repositories/osrf/cloudsim/commit/5601ae82a4a3.json"}, "html": {"href": "#!/osrf/cloudsim/commits/5601ae82a4a3"}}}, "repository": {"links": {"self": {"href": "data/repositories/osrf/cloudsim.json"}, "html": {"href": "#!/osrf/cloudsim"}, "avatar": {"href": "data/bytebucket.org/ravatar/{5f891f62-80d7-4c6b-b39b-41fe459fdda9}ts=default"}}, "type": "repository", "name": "cloudsim", "full_name": "osrf/cloudsim", "uuid": "{5f891f62-80d7-4c6b-b39b-41fe459fdda9}"}, "branch": {"name": "keys and machine types"}}, "state": "OPEN", "author": {"display_name": "Hugo Boyer", "uuid": "{3d87874e-7099-4981-b04f-57f0272faa7d}", "links": {"self": {"href": "https://api.bitbucket.org/2.0/users/%7B3d87874e-7099-4981-b04f-57f0272faa7d%7D"}, "html": {"href": "https://bitbucket.org/%7B3d87874e-7099-4981-b04f-57f0272faa7d%7D/"}, "avatar": {"href": "data/secure.gravatar.com/avatar/21198da8539b599e3633017f5f5f8150d=httpsavatar-management--avatars.us-west-2.prod.public.atl-paas.netinitialsHB-6.png"}}, "nickname": "hugomatic", "type": "user", "account_id": "557058:869c02bb-b246-4cdc-9db3-0064e8add185"}, "date": "2016-09-01T20:45:19.433709+00:00"}, "pull_request": {"type": "pullrequest", "id": 3, "links": {"self": {"href": "data/repositories/osrf/cloudsim/pullrequests/3.json"}, "html": {"href": "#!/osrf/cloudsim/pull-requests/3"}}, "title": "keys and machine types"}}, {"update": {"description": "Added new projects", "title": "keys and machine types", "destination": {"commit": {"hash": "94fcab407d62", "type": "commit", "links": {"self": {"href": "data/repositories/osrf/cloudsim/commit/94fcab407d62.json"}, "html": {"href": "#!/osrf/cloudsim/commits/94fcab407d62"}}}, "repository": {"links": {"self": {"href": "data/repositories/osrf/cloudsim.json"}, "html": {"href": "#!/osrf/cloudsim"}, "avatar": {"href": "data/bytebucket.org/ravatar/{5f891f62-80d7-4c6b-b39b-41fe459fdda9}ts=default"}}, "type": "repository", "name": "cloudsim", "full_name": "osrf/cloudsim", "uuid": "{5f891f62-80d7-4c6b-b39b-41fe459fdda9}"}, "branch": {"name": "default"}}, "reason": "", "source": {"commit": {"hash": "5601ae82a4a3", "type": "commit", "links": {"self": {"href": "data/repositories/osrf/cloudsim/commit/5601ae82a4a3.json"}, "html": {"href": "#!/osrf/cloudsim/commits/5601ae82a4a3"}}}, "repository": {"links": {"self": {"href": "data/repositories/osrf/cloudsim.json"}, "html": {"href": "#!/osrf/cloudsim"}, "avatar": {"href": "data/bytebucket.org/ravatar/{5f891f62-80d7-4c6b-b39b-41fe459fdda9}ts=default"}}, "type": "repository", "name": "cloudsim", "full_name": "osrf/cloudsim", "uuid": "{5f891f62-80d7-4c6b-b39b-41fe459fdda9}"}, "branch": {"name": "keys and machine types"}}, "state": "OPEN", "author": {"display_name": "Hugo Boyer", "uuid": "{3d87874e-7099-4981-b04f-57f0272faa7d}", "links": {"self": {"href": "https://api.bitbucket.org/2.0/users/%7B3d87874e-7099-4981-b04f-57f0272faa7d%7D"}, "html": {"href": "https://bitbucket.org/%7B3d87874e-7099-4981-b04f-57f0272faa7d%7D/"}, "avatar": {"href": "data/secure.gravatar.com/avatar/21198da8539b599e3633017f5f5f8150d=httpsavatar-management--avatars.us-west-2.prod.public.atl-paas.netinitialsHB-6.png"}}, "nickname": "hugomatic", "type": "user", "account_id": "557058:869c02bb-b246-4cdc-9db3-0064e8add185"}, "date": "2016-09-01T20:45:19.414242+00:00"}, "pull_request": {"type": "pullrequest", "id": 3, "links": {"self": {"href": "data/repositories/osrf/cloudsim/pullrequests/3.json"}, "html": {"href": "#!/osrf/cloudsim/pull-requests/3"}}, "title": "keys and machine types"}}]}