{"links": {"self": {"href": "data/repositories/osrf/gazebo_experimental/pullrequests/36/comments/41087739.json"}, "html": {"href": "#!/osrf/gazebo_experimental/pull-requests/36/_/diff#comment-41087739"}}, "parent": {"id": 41065539, "links": {"self": {"href": "data/repositories/osrf/gazebo_experimental/pullrequests/36/comments/41065539.json"}, "html": {"href": "#!/osrf/gazebo_experimental/pull-requests/36/_/diff#comment-41065539"}}}, "deleted": false, "pullrequest": {"type": "pullrequest", "id": 36, "links": {"self": {"href": "data/repositories/osrf/gazebo_experimental/pullrequests/36.json"}, "html": {"href": "#!/osrf/gazebo_experimental/pull-requests/36"}}, "title": "Components defined by protobuf files"}, "content": {"raw": "Added 2ec3d62\n\nexample\n```\n#!C++\n/* ***********************************\n * ******** GENERATED FILE ***********\n * *      Do not edit directly       *\n * ***********************************\n * This file was generated on 2017-07-19 09:26:35.569498 using the command\n * ['/build/gzex_ws/src/gazebo_experimental/src/components/protoc-gen-PIMPL-CPP']\n * from the file\n * gazebo/components/Matrix3d.proto\n * ***********************************\n */\n```", "markup": "markdown", "html": "<p>Added <a href=\"#!/osrf/gazebo_experimental/commits/2ec3d62\" rel=\"nofollow\" class=\"ap-connect-link\">2ec3d62</a></p>\n<p>example</p>\n<div class=\"codehilite language-c++\"><pre><span></span><span class=\"cm\">/* ***********************************</span>\n<span class=\"cm\"> * ******** GENERATED FILE ***********</span>\n<span class=\"cm\"> * *      Do not edit directly       *</span>\n<span class=\"cm\"> * ***********************************</span>\n<span class=\"cm\"> * This file was generated on 2017-07-19 09:26:35.569498 using the command</span>\n<span class=\"cm\"> * [&#39;/build/gzex_ws/src/gazebo_experimental/src/components/protoc-gen-PIMPL-CPP&#39;]</span>\n<span class=\"cm\"> * from the file</span>\n<span class=\"cm\"> * gazebo/components/Matrix3d.proto</span>\n<span class=\"cm\"> * ***********************************</span>\n<span class=\"cm\"> */</span>\n</pre></div>", "type": "rendered"}, "created_on": "2017-07-19T16:29:59.598910+00:00", "user": {"display_name": "Shane Loretz", "uuid": "{656e3311-aad9-45a1-aaf7-b0ee0e84b287}", "links": {"self": {"href": "https://api.bitbucket.org/2.0/users/%7B656e3311-aad9-45a1-aaf7-b0ee0e84b287%7D"}, "html": {"href": "https://bitbucket.org/%7B656e3311-aad9-45a1-aaf7-b0ee0e84b287%7D/"}, "avatar": {"href": "https://avatar-management--avatars.us-west-2.prod.public.atl-paas.net/557058:684383ab-ac95-4859-a350-4a6f41a94a22/c7a1ebf5-cade-4115-9f26-9d3facb776db/128"}}, "nickname": "Shane Loretz", "type": "user", "account_id": "557058:684383ab-ac95-4859-a350-4a6f41a94a22"}, "updated_on": "2017-07-19T16:30:10.228352+00:00", "type": "pullrequest_comment", "id": 41087739}