{"changes": {"content": {"new": "Hi,\r\nWe have the following configuration: a named \"C11_Agent\" running in the field computer and a named \"c11\" node running on a local computer.\r\nThe two nodes communicate with ROS.\r\nHowever, if the communication from the local  to the field computer is w", "old": "Hi,\r\nWe have the following configuration: a named \"C11_Agent\" running in the field computer and a named \"c11\" node running on a local computer.\r\nThe two nodes communicate with ROS.\r\nHowever, if the communication from the local  to the field computer is w"}}, "links": {"self": {"href": "data/repositories/osrf/cloudsim-legacy/issues/49/changes/3309473.json"}, "html": {"href": "#!/osrf/cloudsim-legacy/issues/49#comment-3309473"}}, "issue": {"links": {"self": {"href": "data/repositories/osrf/cloudsim-legacy/issues/49.json"}}, "type": "issue", "id": 49, "repository": {"links": {"self": {"href": "data/repositories/osrf/cloudsim-legacy.json"}, "html": {"href": "#!/osrf/cloudsim-legacy"}, "avatar": {"href": "data/bytebucket.org/ravatar/{e799e7f6-0caa-464a-97f8-8605a37ebfb1}ts=python"}}, "type": "repository", "name": "cloudsim-legacy", "full_name": "osrf/cloudsim-legacy", "uuid": "{e799e7f6-0caa-464a-97f8-8605a37ebfb1}"}, "title": "ROS Network is not working properly from the field computer to the local computer"}, "created_on": "2013-03-04T23:01:03.878414+00:00", "user": {"display_name": "John Hsu", "uuid": "{0a186eae-abf0-4514-a951-23db5eccc286}", "links": {"self": {"href": "https://api.bitbucket.org/2.0/users/%7B0a186eae-abf0-4514-a951-23db5eccc286%7D"}, "html": {"href": "https://bitbucket.org/%7B0a186eae-abf0-4514-a951-23db5eccc286%7D/"}, "avatar": {"href": "https://avatar-management--avatars.us-west-2.prod.public.atl-paas.net/557058:f3968cd3-4910-4384-8349-482a6c7889ec/5445ce6e-6273-47f0-84eb-621c86ca11cb/128"}}, "nickname": "hsu", "type": "user", "account_id": "557058:f3968cd3-4910-4384-8349-482a6c7889ec"}, "message": {"raw": null, "markup": "markdown", "html": "", "type": "rendered"}, "type": "issue_change", "id": 3309473}