{"links": {"self": {"href": "data/repositories/osrf/cloudsim-legacy/pullrequests/156/comments/870428.json"}, "html": {"href": "#!/osrf/cloudsim-legacy/pull-requests/156/_/diff#comment-870428"}}, "parent": {"id": 870200, "links": {"self": {"href": "data/repositories/osrf/cloudsim-legacy/pullrequests/156/comments/870200.json"}, "html": {"href": "#!/osrf/cloudsim-legacy/pull-requests/156/_/diff#comment-870200"}}}, "deleted": false, "pullrequest": {"type": "pullrequest", "id": 156, "links": {"self": {"href": "data/repositories/osrf/cloudsim-legacy/pullrequests/156.json"}, "html": {"href": "#!/osrf/cloudsim-legacy/pull-requests/156"}}, "title": "fixed the zipping issue, and added to the integration test"}, "content": {"raw": "I don't know why, but the test passed for me.  In case it's relevant, I have this in my `boto.ini`:\n\n~~~\n[Boto]\nec2_region_name = us-east-1a\nec2_region_endpoint = ec2.us-east-1.amazonaws.com\n~~~", "markup": "markdown", "html": "<p>I don't know why, but the test passed for me.  In case it's relevant, I have this in my <code>boto.ini</code>:</p>\n<div class=\"codehilite\"><pre><span></span><span class=\"k\">[Boto]</span>\n<span class=\"na\">ec2_region_name</span> <span class=\"o\">=</span> <span class=\"s\">us-east-1a</span>\n<span class=\"na\">ec2_region_endpoint</span> <span class=\"o\">=</span> <span class=\"s\">ec2.us-east-1.amazonaws.com</span>\n</pre></div>", "type": "rendered"}, "created_on": "2013-11-26T19:12:02.054263+00:00", "user": {"display_name": "Brian Gerkey", "uuid": "{3d8b5763-9dad-4be7-85c2-a7ab6cd49173}", "links": {"self": {"href": "https://api.bitbucket.org/2.0/users/%7B3d8b5763-9dad-4be7-85c2-a7ab6cd49173%7D"}, "html": {"href": "https://bitbucket.org/%7B3d8b5763-9dad-4be7-85c2-a7ab6cd49173%7D/"}, "avatar": {"href": "https://avatar-management--avatars.us-west-2.prod.public.atl-paas.net/557058:2e35028e-9ad8-4d6a-a3a5-275159a304a9/5fa9ec73-0fec-4860-a202-e34ae23b6a12/128"}}, "nickname": "Brian Gerkey", "type": "user", "account_id": "557058:2e35028e-9ad8-4d6a-a3a5-275159a304a9"}, "updated_on": "2013-11-26T19:12:02.068969+00:00", "type": "pullrequest_comment", "id": 870428}