{"priority": "minor", "kind": "bug", "repository": {"links": {"self": {"href": "data/repositories/osrf/cloudsim-legacy.json"}, "html": {"href": "#!/osrf/cloudsim-legacy"}, "avatar": {"href": "data/bytebucket.org/ravatar/{e799e7f6-0caa-464a-97f8-8605a37ebfb1}ts=python"}}, "type": "repository", "name": "cloudsim-legacy", "full_name": "osrf/cloudsim-legacy", "uuid": "{e799e7f6-0caa-464a-97f8-8605a37ebfb1}"}, "links": {"attachments": {"href": "data/repositories/osrf/cloudsim-legacy/issues/87/attachments_page=1.json"}, "self": {"href": "data/repositories/osrf/cloudsim-legacy/issues/87.json"}, "watch": {"href": "https://api.bitbucket.org/2.0/repositories/osrf/cloudsim-legacy/issues/87/watch"}, "comments": {"href": "data/repositories/osrf/cloudsim-legacy/issues/87/comments_page=1.json"}, "html": {"href": "#!/osrf/cloudsim-legacy/issues/87/redirect-users-to-login-page-when-they-log"}, "vote": {"href": "https://api.bitbucket.org/2.0/repositories/osrf/cloudsim-legacy/issues/87/vote"}}, "reporter": {"display_name": "Steffi Paepcke", "uuid": "{88ec2edf-5653-4e93-b139-6f2418d9fde5}", "links": {"self": {"href": "https://api.bitbucket.org/2.0/users/%7B88ec2edf-5653-4e93-b139-6f2418d9fde5%7D"}, "html": {"href": "https://bitbucket.org/%7B88ec2edf-5653-4e93-b139-6f2418d9fde5%7D/"}, "avatar": {"href": "https://bitbucket.org/account/spaepcke/avatar/"}}, "nickname": "spaepcke", "type": "user", "account_id": null}, "title": "Redirect users to Login page when they Log out", "component": null, "votes": 0, "watches": 2, "content": {"raw": "Participant 4 logged out and was not taken where he was expecting to go. Logging out should take users back to the login page\r\n\r\nHe also mentioned that a \"Sign in as a different user\" option would be nice to have", "markup": "markdown", "html": "<p>Participant 4 logged out and was not taken where he was expecting to go. Logging out should take users back to the login page</p>\n<p>He also mentioned that a \"Sign in as a different user\" option would be nice to have</p>", "type": "rendered"}, "assignee": null, "state": "resolved", "version": {"name": "1.5", "links": {"self": {"href": "data/repositories/osrf/cloudsim-legacy/versions/54079.json"}}}, "edited_on": null, "created_on": "2013-03-29T21:34:48.933858+00:00", "milestone": {"name": "NRI tutorial", "links": {"self": {"href": "data/repositories/osrf/cloudsim-legacy/milestones/79443.json"}}}, "updated_on": "2013-09-24T00:05:43.250896+00:00", "type": "issue", "id": 87}