{"priority": "minor", "kind": "proposal", "repository": {"links": {"self": {"href": "data/repositories/osrf/cloudsim-legacy.json"}, "html": {"href": "#!/osrf/cloudsim-legacy"}, "avatar": {"href": "data/bytebucket.org/ravatar/{e799e7f6-0caa-464a-97f8-8605a37ebfb1}ts=python"}}, "type": "repository", "name": "cloudsim-legacy", "full_name": "osrf/cloudsim-legacy", "uuid": "{e799e7f6-0caa-464a-97f8-8605a37ebfb1}"}, "links": {"attachments": {"href": "data/repositories/osrf/cloudsim-legacy/issues/88/attachments_page=1.json"}, "self": {"href": "data/repositories/osrf/cloudsim-legacy/issues/88.json"}, "watch": {"href": "https://api.bitbucket.org/2.0/repositories/osrf/cloudsim-legacy/issues/88/watch"}, "comments": {"href": "data/repositories/osrf/cloudsim-legacy/issues/88/comments_page=1.json"}, "html": {"href": "#!/osrf/cloudsim-legacy/issues/88/discuss-task-queuing"}, "vote": {"href": "https://api.bitbucket.org/2.0/repositories/osrf/cloudsim-legacy/issues/88/vote"}}, "reporter": {"display_name": "Steffi Paepcke", "uuid": "{88ec2edf-5653-4e93-b139-6f2418d9fde5}", "links": {"self": {"href": "https://api.bitbucket.org/2.0/users/%7B88ec2edf-5653-4e93-b139-6f2418d9fde5%7D"}, "html": {"href": "https://bitbucket.org/%7B88ec2edf-5653-4e93-b139-6f2418d9fde5%7D/"}, "avatar": {"href": "https://bitbucket.org/account/spaepcke/avatar/"}}, "nickname": "spaepcke", "type": "user", "account_id": null}, "title": "Discuss Task queuing", "component": null, "votes": 0, "watches": 2, "content": {"raw": "P4 was unsure of what happens when he clicks Start on a task. He expected it to queue that Task to run next so that he can queue a bunch of tasks and let them run automatically, in order. Should we do this, or require users to manually click Start when the previous task has completed?", "markup": "markdown", "html": "<p>P4 was unsure of what happens when he clicks Start on a task. He expected it to queue that Task to run next so that he can queue a bunch of tasks and let them run automatically, in order. Should we do this, or require users to manually click Start when the previous task has completed?</p>", "type": "rendered"}, "assignee": null, "state": "open", "version": null, "edited_on": null, "created_on": "2013-03-29T22:47:45.348422+00:00", "milestone": null, "updated_on": "2013-07-23T00:17:34.739247+00:00", "type": "issue", "id": 88}