{"pagelen": 100, "values": [{"links": {"self": {"href": "data/repositories/osrf/cloudsimk/pullrequests/42/comments/2078358.json"}, "code": {"href": "https://api.bitbucket.org/2.0/repositories/osrf/cloudsimk/diff/osrf/cloudsimk:0769ceb14ce8..265e4978a1df?path=app%2Fcontrollers%2Fbilling.js"}, "html": {"href": "#!/osrf/cloudsimk/pull-requests/42/_/diff#comment-2078358"}}, "deleted": false, "pullrequest": {"type": "pullrequest", "id": 42, "links": {"self": {"href": "data/repositories/osrf/cloudsimk/pullrequests/42.json"}, "html": {"href": "#!/osrf/cloudsimk/pull-requests/42"}}, "title": "Paypal integration"}, "content": {"raw": " These console.log prints should be put together in a single line, that also specifies that a Paypal payment has completed.\nOr we could remove the console.log calls completely, but a Paypal payment is a noteworthy and rare event.\nPS: these look like debug prints I may have something to do with.", "markup": "markdown", "html": "<p>These console.log prints should be put together in a single line, that also specifies that a Paypal payment has completed.\nOr we could remove the console.log calls completely, but a Paypal payment is a noteworthy and rare event.\nPS: these look like debug prints I may have something to do with.</p>", "type": "rendered"}, "created_on": "2014-06-06T22:55:12.930674+00:00", "user": {"display_name": "Hugo Boyer", "uuid": "{3d87874e-7099-4981-b04f-57f0272faa7d}", "links": {"self": {"href": "https://api.bitbucket.org/2.0/users/%7B3d87874e-7099-4981-b04f-57f0272faa7d%7D"}, "html": {"href": "https://bitbucket.org/%7B3d87874e-7099-4981-b04f-57f0272faa7d%7D/"}, "avatar": {"href": "data/secure.gravatar.com/avatar/21198da8539b599e3633017f5f5f8150d=httpsavatar-management--avatars.us-west-2.prod.public.atl-paas.netinitialsHB-6.png"}}, "nickname": "hugomatic", "type": "user", "account_id": "557058:869c02bb-b246-4cdc-9db3-0064e8add185"}, "inline": {"to": 27, "from": null, "path": "app/controllers/billing.js"}, "updated_on": "2014-06-06T22:55:12.936960+00:00", "type": "pullrequest_comment", "id": 2078358}, {"links": {"self": {"href": "data/repositories/osrf/cloudsimk/pullrequests/42/comments/2117344.json"}, "code": {"href": "https://api.bitbucket.org/2.0/repositories/osrf/cloudsimk/diff/osrf/cloudsimk:None..None?path=app%2Fcontrollers%2Fbilling.js"}, "html": {"href": "#!/osrf/cloudsimk/pull-requests/42/_/diff#comment-2117344"}}, "parent": {"id": 2078358, "links": {"self": {"href": "data/repositories/osrf/cloudsimk/pullrequests/42/comments/2078358.json"}, "html": {"href": "#!/osrf/cloudsimk/pull-requests/42/_/diff#comment-2078358"}}, "depth": 1}, "deleted": false, "pullrequest": {"type": "pullrequest", "id": 42, "links": {"self": {"href": "data/repositories/osrf/cloudsimk/pullrequests/42.json"}, "html": {"href": "#!/osrf/cloudsimk/pull-requests/42"}}, "title": "Paypal integration"}, "content": {"raw": "removed logs f99680b", "markup": "markdown", "html": "<p>removed logs <a href=\"#!/osrf/cloudsimk/commits/f99680b\" rel=\"nofollow\" class=\"ap-connect-link\">f99680b</a></p>", "type": "rendered"}, "created_on": "2014-06-12T01:23:12.201005+00:00", "user": {"display_name": "Ian Chen", "uuid": "{eaa6fca5-6deb-43f6-907f-971c144735dd}", "links": {"self": {"href": "https://api.bitbucket.org/2.0/users/%7Beaa6fca5-6deb-43f6-907f-971c144735dd%7D"}, "html": {"href": "https://bitbucket.org/%7Beaa6fca5-6deb-43f6-907f-971c144735dd%7D/"}, "avatar": {"href": "https://avatar-management--avatars.us-west-2.prod.public.atl-paas.net/557058:10b01d41-a2e9-4a41-a907-e6e2f03b6cd5/1e4adcdf-1946-4280-9aea-eb5f15a7f912/128"}}, "nickname": "Ian Chen", "type": "user", "account_id": "557058:10b01d41-a2e9-4a41-a907-e6e2f03b6cd5"}, "inline": {"to": null, "from": null, "path": "app/controllers/billing.js"}, "updated_on": "2014-06-12T01:23:12.211226+00:00", "type": "pullrequest_comment", "id": 2117344}, {"links": {"self": {"href": "data/repositories/osrf/cloudsimk/pullrequests/42/comments/2222441.json"}, "code": {"href": "https://api.bitbucket.org/2.0/repositories/osrf/cloudsimk/diff/osrf/cloudsimk:f99680b000b4..5b208939ed7c?path=public%2Fviews%2Fusers%2Fpreferences.html"}, "html": {"href": "#!/osrf/cloudsimk/pull-requests/42/_/diff#comment-2222441"}}, "deleted": true, "pullrequest": {"type": "pullrequest", "id": 42, "links": {"self": {"href": "data/repositories/osrf/cloudsimk/pullrequests/42.json"}, "html": {"href": "#!/osrf/cloudsimk/pull-requests/42"}}, "title": "Paypal integration"}, "content": {"raw": "", "markup": "markdown", "html": "", "type": "rendered"}, "created_on": "2014-06-24T17:08:37.240656+00:00", "user": {"display_name": "Nate Koenig", "uuid": "{c862cdd9-fcc8-4419-9fc7-e20db14b8fcb}", "links": {"self": {"href": "https://api.bitbucket.org/2.0/users/%7Bc862cdd9-fcc8-4419-9fc7-e20db14b8fcb%7D"}, "html": {"href": "https://bitbucket.org/%7Bc862cdd9-fcc8-4419-9fc7-e20db14b8fcb%7D/"}, "avatar": {"href": "https://avatar-management--avatars.us-west-2.prod.public.atl-paas.net/557058:095b1e12-74ed-4e20-b44f-2f0745b616e0/ca24bb11-4787-4b14-a20d-d91835e9bde2/128"}}, "nickname": "Nathan Koenig", "type": "user", "account_id": "557058:095b1e12-74ed-4e20-b44f-2f0745b616e0"}, "inline": {"to": 83, "from": null, "path": "public/views/users/preferences.html"}, "updated_on": "2014-06-24T17:09:42.493294+00:00", "type": "pullrequest_comment", "id": 2222441}], "page": 1, "size": 3}